ruamel/ext/msgpack/__init__.py
ruamel.ext.msgpack-0.2.2.dist-info/METADATA
ruamel.ext.msgpack-0.2.2.dist-info/WHEEL
ruamel.ext.msgpack-0.2.2.dist-info/entry_points.txt
ruamel.ext.msgpack-0.2.2.dist-info/top_level.txt
ruamel.ext.msgpack-0.2.2.dist-info/RECORD
