Metadata-Version: 2.1
Name: ruamel.ext.msgpack
Version: 0.2.2
Summary: thin wrapper around msgpack to deal with naive datetime and ruamel defined extension types
Home-page: https://sourceforge.net/p/ruamel-ext-msgpack/code/ci/default/tree
Author: Anthon van der Neut
Author-email: a.van.der.neut@ruamel.eu
License: Copyright Ruamel bvba 2007-2023
Keywords: pypi statistics
Classifier: Development Status :: 4 - Beta
Classifier: Intended Audience :: Developers
Classifier: License :: Other/Proprietary License
Classifier: Operating System :: OS Independent
Classifier: Programming Language :: Python
Requires-Python: >=3
Requires-Dist: msgpack (>=1.0.4)
